Metadata-Version: 2.1
Name: odoo13-addon-muk-web-theme
Version: 13.0.1.0.6
Summary: Odoo Community Backend Theme
Home-page: http://www.mukit.at
Author: MuK IT
License: LGPL-3
Platform: UNKNOWN
Classifier: Programming Language :: Python
Classifier: Framework :: Odoo
Classifier: License :: OSI Approved :: GNU Lesser General Public License v3 (LGPLv3)
Requires-Python: >=3.5
Requires-Dist: odoo13-addon-muk-web-utils
Requires-Dist: odoo (<13.1dev,>=13.0a)
